CHANGES.txt
MANIFEST.in
README.txt
setup.cfg
setup.py
src/slapos/__init__.py
src/slapos.tool.nosqltester.egg-info/PKG-INFO
src/slapos.tool.nosqltester.egg-info/SOURCES.txt
src/slapos.tool.nosqltester.egg-info/dependency_links.txt
src/slapos.tool.nosqltester.egg-info/entry_points.txt
src/slapos.tool.nosqltester.egg-info/namespace_packages.txt
src/slapos.tool.nosqltester.egg-info/requires.txt
src/slapos.tool.nosqltester.egg-info/top_level.txt
src/slapos/tool/__init__.py
src/slapos/tool/nosqltester/__init__.py