Metadata-Version: 1.0
Name: slapos.tool.nosqltester
Version: 0.0.3.dev
Summary: NoSQL systems tester
Home-page: UNKNOWN
Author: Guillaume Bottex, for Nexedi
Author-email: gbottex@tiolive.com
License: GPL
Keywords: nosql test
Platform: UNKNOWN
